{
    "/js/modules/manifest.js": "/js/modules/manifest.js?id=6a4eb117ddc7ca47286f",
    "/js/modules/manifest.js.map": "/js/modules/manifest.js.map?id=302ad5dc81a77672af41",
    "/js/modules/vendor.js": "/js/modules/vendor.js?id=23ec6a96c059e6102de2",
    "/js/modules/vendor.js.map": "/js/modules/vendor.js.map?id=bd399c128735602d4bf5",
    "/js/modules/access.min.js": "/js/modules/access.min.js?id=0869e3d16eb14d570710",
    "/js/modules/access.min.js.map": "/js/modules/access.min.js.map?id=ae9e61ec3b32ecb83bbd",
    "/js/modules/calendar.min.js": "/js/modules/calendar.min.js?id=29c9b1c95a404d546eb3",
    "/js/modules/calendar.min.js.map": "/js/modules/calendar.min.js.map?id=d275d2d0f76fc05d97a4",
    "/js/modules/categories.min.js": "/js/modules/categories.min.js?id=c71cfe85db26eb0127a6",
    "/js/modules/categories.min.js.map": "/js/modules/categories.min.js.map?id=94c0449cc080d1180a87",
    "/js/modules/customers.min.js": "/js/modules/customers.min.js?id=04319aebb33292fcdcb8",
    "/js/modules/customers.min.js.map": "/js/modules/customers.min.js.map?id=7e005d719c643a5133ac",
    "/js/modules/dashboard.min.js": "/js/modules/dashboard.min.js?id=10bbda0a738885f5753d",
    "/css/styles-admin.min.css": "/css/styles-admin.min.css?id=899eca035ff062d5996f",
    "/assets/pdf/css/style.min.css": "/assets/pdf/css/style.min.css?id=8d118988c3daa40301ae",
    "/js/modules/dashboard.min.js.map": "/js/modules/dashboard.min.js.map?id=4c16123feb6cca4816b2",
    "/js/modules/holidays.min.js": "/js/modules/holidays.min.js?id=3fb1d03b6985929d6d91",
    "/js/modules/holidays.min.js.map": "/js/modules/holidays.min.js.map?id=8ac8694df68c8e5ac2f8",
    "/js/modules/icons.min.js": "/js/modules/icons.min.js?id=aa0c54d3118e1c6ede9a",
    "/js/modules/icons.min.js.map": "/js/modules/icons.min.js.map?id=453c621de27688d8d904",
    "/js/modules/logs.min.js": "/js/modules/logs.min.js?id=f4b76c235db1197dee0d",
    "/js/modules/logs.min.js.map": "/js/modules/logs.min.js.map?id=c46261256eb2b4cabc55",
    "/js/modules/module.min.js": "/js/modules/module.min.js?id=bfb28faabbe3d2fc3e39",
    "/js/modules/module.min.js.map": "/js/modules/module.min.js.map?id=80da301370747ad8a48f",
    "/js/modules/page.min.js": "/js/modules/page.min.js?id=da37969770ce971b4ea8",
    "/js/modules/page.min.js.map": "/js/modules/page.min.js.map?id=6d363c8b74e2b90f4f00",
    "/js/modules/presentation.min.js": "/js/modules/presentation.min.js?id=e9acc766f9b5877d0c28",
    "/js/modules/presentation.min.js.map": "/js/modules/presentation.min.js.map?id=6fe4527f42e0a8ed3bdb",
    "/js/modules/products.min.js": "/js/modules/products.min.js?id=440ce0b02de3bbd9ab11",
    "/js/modules/products.min.js.map": "/js/modules/products.min.js.map?id=d7026aa00aff6ab3d987",
    "/js/modules/profile.min.js": "/js/modules/profile.min.js?id=2cbc2738982f83b5246c",
    "/js/modules/profile.min.js.map": "/js/modules/profile.min.js.map?id=f14a96a2e7a01ad0a304",
    "/js/modules/providers.min.js": "/js/modules/providers.min.js?id=73ff0c1add6244fbebac",
    "/js/modules/providers.min.js.map": "/js/modules/providers.min.js.map?id=29fad6361e542f0bdf13",
    "/js/modules/purchase-request.min.js": "/js/modules/purchase-request.min.js?id=464222a3b1f4061ed07c",
    "/js/modules/purchase-request.min.js.map": "/js/modules/purchase-request.min.js.map?id=e5405c7efdcba17513c8",
    "/js/modules/quotation.min.js": "/js/modules/quotation.min.js?id=fb7de715a7937df97cb5",
    "/js/modules/quotation.min.js.map": "/js/modules/quotation.min.js.map?id=76ce519b7b3ecc76a826",
    "/js/modules/role.min.js": "/js/modules/role.min.js?id=5d9dcb4b8fd701e38e33",
    "/js/modules/role.min.js.map": "/js/modules/role.min.js.map?id=1d9b00980dea483bda51",
    "/js/modules/sites.min.js": "/js/modules/sites.min.js?id=4f73659646c1312dce8c",
    "/js/modules/sites.min.js.map": "/js/modules/sites.min.js.map?id=54cba8c2698a67e2d3b5",
    "/js/modules/stock.min.js": "/js/modules/stock.min.js?id=01510dfe404222a25fe7",
    "/js/modules/stock.min.js.map": "/js/modules/stock.min.js.map?id=6fba970459e311e28cab",
    "/js/modules/unity.min.js": "/js/modules/unity.min.js?id=4d5f43b8bf4de9cbc81f",
    "/js/modules/unity.min.js.map": "/js/modules/unity.min.js.map?id=6aa500a72070049c861b",
    "/js/modules/user.min.js": "/js/modules/user.min.js?id=d8b21efa33707c7c3f8d",
    "/js/modules/user.min.js.map": "/js/modules/user.min.js.map?id=dc9063251114bc2366f5",
    "/css/main.min.css": "/css/main.min.css?id=0d4ed2d68c3559194557",
    "/js/jquery-3.2.1.min.js": "/js/jquery-3.2.1.min.js?id=c9f5aeeca3ad37bf2aa0",
    "/js/bootstrap.min.js": "/js/bootstrap.min.js?id=65819b7164872c880e7d",
    "/js/popper.min.js": "/js/popper.min.js?id=3621381129597bf34d48",
    "/js/plugins/pace.min.js": "/js/plugins/pace.min.js?id=248f37358dd94120dc84",
    "/js/plugins/chart.min.js": "/js/plugins/chart.min.js?id=84b51185bbcb3a37eea9",
    "/js/main.min.js": "/js/main.min.js?id=a594f0a6321c33e181e7",
    "/images/logo.png": "/images/logo.png?id=e140dca63402836e3f75",
    "/images/cover-page-default.jpg": "/images/cover-page-default.jpg?id=c761bbbfff71b78863e9",
    "/images/user-default.jpg": "/images/user-default.jpg?id=9396d9f41a14604bf42e",
    "/images/project-4.jpg": "/images/project-4.jpg?id=88e13cc250031548daea",
    "/images/favicon.ico": "/images/favicon.ico?id=6ab725445cde24dfb6b3",
    "/images/not-image-product.png": "/images/not-image-product.png?id=d2c815eceb07f0817879",
    "/images/placeholder-upload.png": "/images/placeholder-upload.png?id=b523b736304894e7e604",
    "/images/marca_agua.png": "/images/marca_agua.png?id=fd8985ea51a945b80b60",
    "/images/generic.png": "/images/generic.png?id=884901f06470a43c6774",
    "/js/login-colaborator.min.js": "/js/login-colaborator.min.js?id=ff28e8e85e8d0cbe6f7c"
}
